odoo/addons/l10n_es_aeat_mod303_vat_prorate/README.rst
odoo/addons/l10n_es_aeat_mod303_vat_prorate/__init__.py
odoo/addons/l10n_es_aeat_mod303_vat_prorate/__manifest__.py
odoo/addons/l10n_es_aeat_mod303_vat_prorate/data/2023/aeat.model.export.config.line.csv
odoo/addons/l10n_es_aeat_mod303_vat_prorate/i18n/ca.po
odoo/addons/l10n_es_aeat_mod303_vat_prorate/i18n/es.po
odoo/addons/l10n_es_aeat_mod303_vat_prorate/i18n/l10n_es_aeat_mod303_vat_prorate.pot
odoo/addons/l10n_es_aeat_mod303_vat_prorate/models/__init__.py
odoo/addons/l10n_es_aeat_mod303_vat_prorate/models/mod303.py
odoo/addons/l10n_es_aeat_mod303_vat_prorate/readme/CONFIGURE.md
odoo/addons/l10n_es_aeat_mod303_vat_prorate/readme/CONTRIBUTORS.md
odoo/addons/l10n_es_aeat_mod303_vat_prorate/readme/DESCRIPTION.md
odoo/addons/l10n_es_aeat_mod303_vat_prorate/readme/ROADMAP.md
odoo/addons/l10n_es_aeat_mod303_vat_prorate/readme/USAGE.md
odoo/addons/l10n_es_aeat_mod303_vat_prorate/static/description/icon.png
odoo/addons/l10n_es_aeat_mod303_vat_prorate/static/description/index.html
odoo/addons/l10n_es_aeat_mod303_vat_prorate/tests/__init__.py
odoo/addons/l10n_es_aeat_mod303_vat_prorate/tests/test_l10n_es_aeat_mod303_vat_prorate.py
odoo/addons/l10n_es_aeat_mod303_vat_prorate/views/mod303_views.xml
odoo_addon_l10n_es_aeat_mod303_vat_prorate-18.0.1.0.2.dist-info/METADATA
odoo_addon_l10n_es_aeat_mod303_vat_prorate-18.0.1.0.2.dist-info/WHEEL
odoo_addon_l10n_es_aeat_mod303_vat_prorate-18.0.1.0.2.dist-info/top_level.txt
odoo_addon_l10n_es_aeat_mod303_vat_prorate-18.0.1.0.2.dist-info/RECORD
